MANIFEST.in
README.rst
setup.py
collective/__init__.py
collective.js.jasmid.egg-info/PKG-INFO
collective.js.jasmid.egg-info/SOURCES.txt
collective.js.jasmid.egg-info/dependency_links.txt
collective.js.jasmid.egg-info/entry_points.txt
collective.js.jasmid.egg-info/namespace_packages.txt
collective.js.jasmid.egg-info/not-zip-safe
collective.js.jasmid.egg-info/requires.txt
collective.js.jasmid.egg-info/top_level.txt
collective/js/__init__.py
collective/js/jasmid/__init__.py
collective/js/jasmid/configure.zcml
collective/js/jasmid/interfaces.py
collective/js/jasmid/upgrades.py
collective/js/jasmid/upgrades.zcml
collective/js/jasmid/example/__init__.py
collective/js/jasmid/example/configure.zcml
collective/js/jasmid/example/jasmid.pt
collective/js/jasmid/example/jasmid.py
collective/js/jasmid/profiles/default/browserlayer.xml
collective/js/jasmid/profiles/default/cssregistry.xml
collective/js/jasmid/profiles/default/jsregistry.xml
collective/js/jasmid/profiles/default/metadata.xml
collective/js/jasmid/profiles/default/skins.xml
collective/js/jasmid/resources/js/audio.js
collective/js/jasmid/resources/js/gui.min.js
collective/js/jasmid/resources/js/midifile.js
collective/js/jasmid/resources/js/replayer.js
collective/js/jasmid/resources/js/stream.js
collective/js/jasmid/resources/js/synth.js
collective/js/jasmid/skins/jasmid/AcrossTheBlackRiver1.mid
collective/js/jasmid/skins/jasmid/da.swf
collective/js/jasmid/skins/jasmid/dynamicaudio.as
collective/js/jasmid/skins/jasmid/dynamicaudio.as.metadata
docs/HISTORY.txt